tme_eu-0.3.1.dist-info/licenses/LICENSE
tmeapi/__init__.py
tmeapi/models.py
tme_eu-0.3.1.dist-info/METADATA
tme_eu-0.3.1.dist-info/WHEEL
tme_eu-0.3.1.dist-info/top_level.txt
tme_eu-0.3.1.dist-info/RECORD
