Metadata-Version: 2.4
Name: tme-eu
Version: 0.3.1
Summary: Api for TME.eu
Requires-Python: >=3.10
License-File: LICENSE
Requires-Dist: httpx
Requires-Dist: pydantic>=2
Dynamic: license-file
